{"learningMethod": "DQN", "learningEpochs": 0, "nets": [{"times": {"old_time": 0, "new_time": 1}, "rewards": [0.6], "actions": ["orange"], "densities": [0, 0, 0, 0, 0, 0], "lights": [[0.0, 0.0, 0.0, 0.0, 0.0, 0.0], [1.0, 1.0, 0.0, 0.0, 0.0, 0.0], [0.0, 0.0, 0.0, 0.0, 0.0, 0.0], [0.0, 0.0, 1.0, 0.0, 0.0, 0.0], [0.0, 0.0, 0.0, 0.0, 0.0, 0.0], [0.0, 0.0, 0.0, 0.0, 1.0, 0.0]]}, {"times": {"old_time": 1, "new_time": 2}, "rewards": [0.6], "actions": ["orange"], "densities": [2.0, 0.0, 0.0, 0.0, 0.0, 0.0], "lights": [[0.0, 0.0, 0.0, 0.0, 0.0, 0.0], [1.0, 0.7, 0.0, 0.0, 0.0, 0.0], [0.0, 0.0, 0.0, 0.0, 0.0, 0.0], [0.0, 0.0, 1.0, 0.0, 0.0, 0.0], [0.0, 0.3, 0.0, 0.0, 0.0, 0.0], [0.0, 0.0, 0.0, 0.0, 1.0, 0.0]]}, {"times": {"old_time": 2, "new_time": 3}, "rewards": [0.6], "actions": [1], "densities": [2.0, 2.0, 0.0, 0.0, 0.0, 0.0], "lights": [[0.0, 0.0, 0.0, 0.0, 0.0, 0.0], [1.0, 0.7, 0.0, 0.0, 0.0, 0.0], [0.0, 0.0, 0.0, 0.0, 0.0, 0.0], [0.0, 0.0, 1.0, 0.0, 0.0, 0.0], [0.0, 0.3, 0.0, 0.0, 0.0, 0.0], [0.0, 0.0, 0.0, 0.0, 1.0, 0.0]]}, {"times": {"old_time": 3, "new_time": 4}, "rewards": [5.18], "actions": [1], "densities": [2.0, 3.4, 0.0, 0.0, 0.6, 0.0], "lights": [[0.0, 0.0, 0.0, 0.0, 0.0, 0.0], [1.0, 0.7, 0.0, 0.0, 0.0, 0.0], [0.0, 0.0, 0.0, 0.0, 0.0, 0.0], [0.0, 0.0, 1.0, 0.0, 0.0, 0.0], [0.0, 0.3, 0.0, 0.0, 0.0, 0.0], [0.0, 0.0, 0.0, 0.0, 1.0, 0.0]]}, {"times": {"old_time": 4, "new_time": 5}, "rewards": [8.134], "actions": [0], "densities": [2.0, 4.38, 0.0, 0.0, 1.02, 0.6], "lights": [[0.0, 0.0, 0.0, 0.0, 0.0, 0.0], [1.0, 1.0, 0.0, 0.0, 0.0, 0.0], [0.0, 0.0, 0.0, 0.0, 0.0, 0.0], [0.0, 0.0, 1.0, 0.0, 0.0, 0.0], [0.0, 0.0, 0.0, 0.0, 0.0, 0.0], [0.0, 0.0, 0.0, 0.0, 1.0, 0.0]]}, {"times": {"old_time": 5, "new_time": 6}, "rewards": [10.4202], "actions": ["orange"], "densities": [2.0, 6.38, 0.0, 0.0, 0.0, 1.02], "lights": [[0.0, 0.0, 0.0, 0.0, 0.0, 0.0], [1.0, 1.0, 0.0, 0.0, 0.0, 0.0], [0.0, 0.0, 0.0, 0.0, 0.0, 0.0], [0.0, 0.0, 1.0, 0.0, 0.0, 0.0], [0.0, 0.0, 0.0, 0.0, 0.0, 0.0], [0.0, 0.0, 0.0, 0.0, 1.0, 0.0]]}, {"times": {"old_time": 6, "new_time": 7}, "rewards": [7.32606], "actions": ["orange"], "densities": [2.0, 8.379999999999999, 0.0, 0.0, 0.0, 0.0], "lights": [[0.0, 0.0, 0.0, 0.0, 0.0, 0.0], [1.0, 0.30000000000000004, 0.0, 0.0, 0.0, 0.0], [0.0, 0.7, 0.0, 0.0, 0.0, 0.0], [0.0, 0.0, 1.0, 0.0, 0.0, 0.0], [0.0, 0.0, 0.0, 0.0, 0.0, 0.0], [0.0, 0.0, 0.0, 0.0, 1.0, 0.0]]}, {"times": {"old_time": 7, "new_time": 8}, "rewards": [4.37206], "actions": [0], "densities": [2.0, 4.514, 5.865999999999999, 0.0, 0.0, 0.0], "lights": [[0.0, 0.0, 0.0, 0.0, 0.0, 0.0], [1.0, 0.30000000000000004, 0.0, 0.0, 0.0, 0.0], [0.0, 0.7, 0.0, 0.0, 0.0, 0.0], [0.0, 0.0, 1.0, 0.0, 0.0, 0.0], [0.0, 0.0, 0.0, 0.0, 0.0, 0.0], [0.0, 0.0, 0.0, 0.0, 1.0, 0.0]]}, {"times": {"old_time": 8, "new_time": 9}, "rewards": [2.0858600000000003], "actions": [1], "densities": [2.0, 3.3542000000000005, 3.1598, 5.865999999999999, 0.0, 0.0], "lights": [[0.0, 0.0, 0.0, 0.0, 0.0, 0.0], [1.0, 1.0, 0.0, 0.0, 0.0, 0.0], [0.0, 0.0, 0.0, 0.0, 0.0, 0.0], [0.0, 0.0, 1.0, 0.0, 0.0, 0.0], [0.0, 0.0, 0.0, 0.0, 0.0, 0.0], [0.0, 0.0, 0.0, 0.0, 1.0, 0.0]]}, {"times": {"old_time": 9, "new_time": 10}, "rewards": [2.068182], "actions": ["orange"], "densities": [2.0, 5.3542000000000005, 0.0, 3.1598, 0.0, 0.0], "lights": [[0.0, 0.0, 0.0, 0.0, 0.0, 0.0], [1.0, 1.0, 0.0, 0.0, 0.0, 0.0], [0.0, 0.0, 0.0, 0.0, 0.0, 0.0], [0.0, 0.0, 1.0, 0.0, 0.0, 0.0], [0.0, 0.0, 0.0, 0.0, 0.0, 0.0], [0.0, 0.0, 0.0, 0.0, 1.0, 0.0]]}, {"times": {"old_time": 10, "new_time": 11}, "rewards": [2.068182], "actions": ["orange"], "densities": [2.0, 7.3542000000000005, 0.0, 0.0, 0.0, 0.0], "lights": [[0.0, 0.0, 0.0, 0.0, 0.0, 0.0], [1.0, 0.7, 0.0, 0.0, 0.0, 0.0], [0.0, 0.0, 0.0, 0.0, 0.0, 0.0], [0.0, 0.0, 1.0, 0.0, 0.0, 0.0], [0.0, 0.3, 0.0, 0.0, 0.0, 0.0], [0.0, 0.0, 0.0, 0.0, 1.0, 0.0]]}, {"times": {"old_time": 11, "new_time": 12}, "rewards": [2.068182], "actions": [1], "densities": [2.0, 7.14794, 0.0, 0.0, 2.20626, 0.0], "lights": [[0.0, 0.0, 0.0, 0.0, 0.0, 0.0], [1.0, 0.7, 0.0, 0.0, 0.0, 0.0], [0.0, 0.0, 0.0, 0.0, 0.0, 0.0], [0.0, 0.0, 1.0, 0.0, 0.0, 0.0], [0.0, 0.3, 0.0, 0.0, 0.0, 0.0], [0.0, 0.0, 0.0, 0.0, 1.0, 0.0]]}, {"times": {"old_time": 12, "new_time": 13}, "rewards": [7.5780306], "actions": [0], "densities": [2.0, 7.003558, 0.0, 0.0, 2.144382, 2.20626], "lights": [[0.0, 0.0, 0.0, 0.0, 0.0, 0.0], [1.0, 1.0, 0.0, 0.0, 0.0, 0.0], [0.0, 0.0, 0.0, 0.0, 0.0, 0.0], [0.0, 0.0, 1.0, 0.0, 0.0, 0.0], [0.0, 0.0, 0.0, 0.0, 0.0, 0.0], [0.0, 0.0, 0.0, 0.0, 1.0, 0.0]]}, {"times": {"old_time": 13, "new_time": 14}, "rewards": [11.25143978], "actions": ["orange"], "densities": [2.0, 9.003558, 0.0, 0.0, 0.0, 2.144382], "lights": [[0.0, 0.0, 0.0, 0.0, 0.0, 0.0], [1.0, 1.0, 0.0, 0.0, 0.0, 0.0], [0.0, 0.0, 0.0, 0.0, 0.0, 0.0], [0.0, 0.0, 1.0, 0.0, 0.0, 0.0], [0.0, 0.0, 0.0, 0.0, 0.0, 0.0], [0.0, 0.0, 0.0, 0.0, 1.0, 0.0]]}, {"times": {"old_time": 14, "new_time": 15}, "rewards": [11.25143978], "actions": ["orange"], "densities": [2.0, 11.003558, 0.0, 0.0, 0.0, 0.0], "lights": [[0.0, 0.0, 0.0, 0.0, 0.0, 0.0], [1.0, 0.30000000000000004, 0.0, 0.0, 0.0, 0.0], [0.0, 0.7, 0.0, 0.0, 0.0, 0.0], [0.0, 0.0, 1.0, 0.0, 0.0, 0.0], [0.0, 0.0, 0.0, 0.0, 0.0, 0.0], [0.0, 0.0, 0.0, 0.0, 1.0, 0.0]]}, {"times": {"old_time": 15, "new_time": 16}, "rewards": [3.67340918], "actions": [0], "densities": [2.0, 5.301067400000001, 7.702490599999999, 0.0, 0.0, 0.0], "lights": [[0.0, 0.0, 0.0, 0.0, 0.0, 0.0], [1.0, 0.30000000000000004, 0.0, 0.0, 0.0, 0.0], [0.0, 0.7, 0.0, 0.0, 0.0, 0.0], [0.0, 0.0, 1.0, 0.0, 0.0, 0.0], [0.0, 0.0, 0.0, 0.0, 0.0, 0.0], [0.0, 0.0, 0.0, 0.0, 1.0, 0.0]]}, {"times": {"old_time": 16, "new_time": 17}, "rewards": [2.272295466], "actions": [1], "densities": [2.0, 3.5903202200000006, 3.7107471800000003, 7.702490599999999, 0.0, 0.0], "lights": [[0.0, 0.0, 0.0, 0.0, 0.0, 0.0], [1.0, 1.0, 0.0, 0.0, 0.0, 0.0], [0.0, 0.0, 0.0, 0.0, 0.0, 0.0], [0.0, 0.0, 1.0, 0.0, 0.0, 0.0], [0.0, 0.0, 0.0, 0.0, 0.0, 0.0], [0.0, 0.0, 0.0, 0.0, 1.0, 0.0]]}, {"times": {"old_time": 17, "new_time": 18}, "rewards": [4.4629022922], "actions": ["orange"], "densities": [2.0, 5.590320220000001, 0.0, 3.7107471800000003, 0.0, 0.0], "lights": [[0.0, 0.0, 0.0, 0.0, 0.0, 0.0], [1.0, 1.0, 0.0, 0.0, 0.0, 0.0], [0.0, 0.0, 0.0, 0.0, 0.0, 0.0], [0.0, 0.0, 1.0, 0.0, 0.0, 0.0], [0.0, 0.0, 0.0, 0.0, 0.0, 0.0], [0.0, 0.0, 0.0, 0.0, 1.0, 0.0]]}, {"times": {"old_time": 18, "new_time": 19}, "rewards": [6.59632707054], "actions": ["orange"], "densities": [2.0, 7.590320220000001, 0.0, 0.0, 0.0, 0.0], "lights": [[0.0, 0.0, 0.0, 0.0, 0.0, 0.0], [1.0, 0.7, 0.0, 0.0, 0.0, 0.0], [0.0, 0.0, 0.0, 0.0, 0.0, 0.0], [0.0, 0.0, 1.0, 0.0, 0.0, 0.0], [0.0, 0.3, 0.0, 0.0, 0.0, 0.0], [0.0, 0.0, 0.0, 0.0, 1.0, 0.0]]}, {"times": {"old_time": 19, "new_time": 20}, "rewards": [4.32403160454], "actions": [1], "densities": [2.0, 7.313224154, 0.0, 0.0, 2.277096066, 0.0], "lights": [[0.0, 0.0, 0.0, 0.0, 0.0, 0.0], [1.0, 0.7, 0.0, 0.0, 0.0, 0.0], [0.0, 0.0, 0.0, 0.0, 0.0, 0.0], [0.0, 0.0, 1.0, 0.0, 0.0, 0.0], [0.0, 0.3, 0.0, 0.0, 0.0, 0.0], [0.0, 0.0, 0.0, 0.0, 1.0, 0.0]]}, {"times": {"old_time": 20, "new_time": 21}, "rewards": [2.1334247783399998], "actions": [1], "densities": [2.0, 7.1192569078, 0.0, 0.0, 2.1939672462, 2.277096066], "lights": [[0.0, 0.0, 0.0, 0.0, 0.0, 0.0], [1.0, 0.7, 0.0, 0.0, 0.0, 0.0], [0.0, 0.0, 0.0, 0.0, 0.0, 0.0], [0.0, 0.0, 1.0, 0.0, 0.0, 0.0], [0.0, 0.3, 0.0, 0.0, 0.0, 0.0], [0.0, 0.0, 0.0, 0.0, 1.0, 0.0]]}, {"times": {"old_time": 21, "new_time": 22}, "rewards": [7.684593804621999], "actions": [0], "densities": [2.0, 6.98347983546, 0.0, 0.0, 2.13577707234, 2.1939672462], "lights": [[0.0, 0.0, 0.0, 0.0, 0.0, 0.0], [1.0, 1.0, 0.0, 0.0, 0.0, 0.0], [0.0, 0.0, 0.0, 0.0, 0.0, 0.0], [0.0, 0.0, 1.0, 0.0, 0.0, 0.0], [0.0, 0.0, 0.0, 0.0, 0.0, 0.0], [0.0, 0.0, 0.0, 0.0, 1.0, 0.0]]}, {"times": {"old_time": 22, "new_time": 23}, "rewards": [11.389971946008599], "actions": ["orange"], "densities": [2.0, 8.983479835459999, 0.0, 0.0, 0.0, 2.13577707234], "lights": [[0.0, 0.0, 0.0, 0.0, 0.0, 0.0], [1.0, 1.0, 0.0, 0.0, 0.0, 0.0], [0.0, 0.0, 0.0, 0.0, 0.0, 0.0], [0.0, 0.0, 1.0, 0.0, 0.0, 0.0], [0.0, 0.0, 0.0, 0.0, 0.0, 0.0], [0.0, 0.0, 0.0, 0.0, 1.0, 0.0]]}, {"times": {"old_time": 23, "new_time": 24}, "rewards": [11.389971946008599], "actions": ["orange"], "densities": [2.0, 10.983479835459999, 0.0, 0.0, 0.0, 0.0], "lights": [[0.0, 0.0, 0.0, 0.0, 0.0, 0.0], [1.0, 0.30000000000000004, 0.0, 0.0, 0.0, 0.0], [0.0, 0.7, 0.0, 0.0, 0.0, 0.0], [0.0, 0.0, 1.0, 0.0, 0.0, 0.0], [0.0, 0.0, 0.0, 0.0, 0.0, 0.0], [0.0, 0.0, 0.0, 0.0, 1.0, 0.0]]}, {"times": {"old_time": 24, "new_time": 25}, "rewards": [3.7053781413866003], "actions": [1], "densities": [2.0, 5.295043950638, 7.688435884821999, 0.0, 0.0, 0.0], "lights": [[0.0, 0.0, 0.0, 0.0, 0.0, 0.0], [1.0, 1.0, 0.0, 0.0, 0.0, 0.0], [0.0, 0.0, 0.0, 0.0, 0.0, 0.0], [0.0, 0.0, 1.0, 0.0, 0.0, 0.0], [0.0, 0.0, 0.0, 0.0, 0.0, 0.0], [0.0, 0.0, 0.0, 0.0, 1.0, 0.0]]}, {"times": {"old_time": 25, "new_time": 26}, "rewards": [2.27640576103542], "actions": ["orange"], "densities": [2.0, 7.295043950638, 0.0, 7.688435884821999, 0.0, 0.0], "lights": [[0.0, 0.0, 0.0, 0.0, 0.0, 0.0], [1.0, 1.0, 0.0, 0.0, 0.0, 0.0], [0.0, 0.0, 0.0, 0.0, 0.0, 0.0], [0.0, 0.0, 1.0, 0.0, 0.0, 0.0], [0.0, 0.0, 0.0, 0.0, 0.0, 0.0], [0.0, 0.0, 0.0, 0.0, 1.0, 0.0]]}, {"times": {"old_time": 26, "new_time": 27}, "rewards": [4.469889793760213], "actions": ["orange"], "densities": [2.0, 9.295043950638, 0.0, 0.0, 0.0, 0.0], "lights": [[0.0, 0.0, 0.0, 0.0, 0.0, 0.0], [1.0, 0.7, 0.0, 0.0, 0.0, 0.0], [0.0, 0.0, 0.0, 0.0, 0.0, 0.0], [0.0, 0.0, 1.0, 0.0, 0.0, 0.0], [0.0, 0.3, 0.0, 0.0, 0.0, 0.0], [0.0, 0.0, 0.0, 0.0, 1.0, 0.0]]}, {"times": {"old_time": 27, "new_time": 28}, "rewards": [6.6053286166675695], "actions": [1], "densities": [2.0, 8.5065307654466, 0.0, 0.0, 2.7885131851914, 0.0], "lights": [[0.0, 0.0, 0.0, 0.0, 0.0, 0.0], [1.0, 0.7, 0.0, 0.0, 0.0, 0.0], [0.0, 0.0, 0.0, 0.0, 0.0, 0.0], [0.0, 0.0, 1.0, 0.0, 0.0, 0.0], [0.0, 0.3, 0.0, 0.0, 0.0, 0.0], [0.0, 0.0, 0.0, 0.0, 1.0, 0.0]]}, {"times": {"old_time": 28, "new_time": 29}, "rewards": [6.423730031667297], "actions": [0], "densities": [2.0, 7.95457153581262, 0.0, 0.0, 2.55195922963398, 2.7885131851914], "lights": [[0.0, 0.0, 0.0, 0.0, 0.0, 0.0], [1.0, 1.0, 0.0, 0.0, 0.0, 0.0], [0.0, 0.0, 0.0, 0.0, 0.0, 0.0], [0.0, 0.0, 1.0, 0.0, 0.0, 0.0], [0.0, 0.0, 0.0, 0.0, 0.0, 0.0], [0.0, 0.0, 0.0, 0.0, 1.0, 0.0]]}, {"times": {"old_time": 29, "new_time": 30}, "rewards": [6.296611022167108], "actions": ["orange"], "densities": [2.0, 9.954571535812619, 0.0, 0.0, 0.0, 2.55195922963398], "lights": [[0.0, 0.0, 0.0, 0.0, 0.0, 0.0], [1.0, 1.0, 0.0, 0.0, 0.0, 0.0], [0.0, 0.0, 0.0, 0.0, 0.0, 0.0], [0.0, 0.0, 1.0, 0.0, 0.0, 0.0], [0.0, 0.0, 0.0, 0.0, 0.0, 0.0], [0.0, 0.0, 0.0, 0.0, 1.0, 0.0]]}, {"times": {"old_time": 30, "new_time": 31}, "rewards": [6.207627715516975], "actions": ["orange"], "densities": [2.0, 11.954571535812619, 0.0, 0.0, 0.0, 0.0], "lights": [[0.0, 0.0, 0.0, 0.0, 0.0, 0.0], [1.0, 0.30000000000000004, 0.0, 0.0, 0.0, 0.0], [0.0, 0.7, 0.0, 0.0, 0.0, 0.0], [0.0, 0.0, 1.0, 0.0, 0.0, 0.0], [0.0, 0.0, 0.0, 0.0, 0.0, 0.0], [0.0, 0.0, 0.0, 0.0, 1.0, 0.0]]}, {"times": {"old_time": 31, "new_time": 32}, "rewards": [6.145339400861882], "actions": [0], "densities": [2.0, 5.586371460743786, 8.368200075068833, 0.0, 0.0, 0.0], "lights": [[0.0, 0.0, 0.0, 0.0, 0.0, 0.0], [1.0, 0.30000000000000004, 0.0, 0.0, 0.0, 0.0], [0.0, 0.7, 0.0, 0.0, 0.0, 0.0], [0.0, 0.0, 1.0, 0.0, 0.0, 0.0], [0.0, 0.0, 0.0, 0.0, 0.0, 0.0], [0.0, 0.0, 0.0, 0.0, 1.0, 0.0]]}, {"times": {"old_time": 32, "new_time": 33}, "rewards": [6.101737580603317], "actions": [1], "densities": [2.0, 3.675911438223136, 3.91046002252065, 8.368200075068833, 0.0, 0.0], "lights": [[0.0, 0.0, 0.0, 0.0, 0.0, 0.0], [1.0, 1.0, 0.0, 0.0, 0.0, 0.0], [0.0, 0.0, 0.0, 0.0, 0.0, 0.0], [0.0, 0.0, 1.0, 0.0, 0.0, 0.0], [0.0, 0.0, 0.0, 0.0, 0.0, 0.0], [0.0, 0.0, 0.0, 0.0, 1.0, 0.0]]}, {"times": {"old_time": 33, "new_time": 34}, "rewards": [4.055282064346095], "actions": ["orange"], "densities": [2.0, 5.675911438223136, 0.0, 3.91046002252065, 0.0, 0.0], "lights": [[0.0, 0.0, 0.0, 0.0, 0.0, 0.0], [1.0, 1.0, 0.0, 0.0, 0.0, 0.0], [0.0, 0.0, 0.0, 0.0, 0.0, 0.0], [0.0, 0.0, 1.0, 0.0, 0.0, 0.0], [0.0, 0.0, 0.0, 0.0, 0.0, 0.0], [0.0, 0.0, 0.0, 0.0, 1.0, 0.0]]}, {"times": {"old_time": 34, "new_time": 35}, "rewards": [2.022763202966039], "actions": ["orange"], "densities": [2.0, 7.675911438223136, 0.0, 0.0, 0.0, 0.0], "lights": [[0.0, 0.0, 0.0, 0.0, 0.0, 0.0], [1.0, 0.7, 0.0, 0.0, 0.0, 0.0], [0.0, 0.0, 0.0, 0.0, 0.0, 0.0], [0.0, 0.0, 1.0, 0.0, 0.0, 0.0], [0.0, 0.3, 0.0, 0.0, 0.0, 0.0], [0.0, 0.0, 0.0, 0.0, 1.0, 0.0]]}, {"times": {"old_time": 35, "new_time": 36}, "rewards": [7.50384656484453], "actions": [1], "densities": [2.0, 7.373138006756195, 0.0, 0.0, 2.3027734314669406, 0.0], "lights": [[0.0, 0.0, 0.0, 0.0, 0.0, 0.0], [1.0, 0.7, 0.0, 0.0, 0.0, 0.0], [0.0, 0.0, 0.0, 0.0, 0.0, 0.0], [0.0, 0.0, 1.0, 0.0, 0.0, 0.0], [0.0, 0.3, 0.0, 0.0, 0.0, 0.0], [0.0, 0.0, 0.0, 0.0, 1.0, 0.0]]}, {"times": {"old_time": 36, "new_time": 37}, "rewards": [11.155000534297889], "actions": [0], "densities": [2.0, 7.161196604729336, 0.0, 0.0, 2.2119414020268584, 2.3027734314669406], "lights": [[0.0, 0.0, 0.0, 0.0, 0.0, 0.0], [1.0, 1.0, 0.0, 0.0, 0.0, 0.0], [0.0, 0.0, 0.0, 0.0, 0.0, 0.0], [0.0, 0.0, 1.0, 0.0, 0.0, 0.0], [0.0, 0.0, 0.0, 0.0, 0.0, 0.0], [0.0, 0.0, 0.0, 0.0, 1.0, 0.0]]}, {"times": {"old_time": 37, "new_time": 38}, "rewards": [11.155000534297889], "actions": ["orange"], "densities": [2.0, 9.161196604729337, 0.0, 0.0, 0.0, 2.2119414020268584], "lights": [[0.0, 0.0, 0.0, 0.0, 0.0, 0.0], [1.0, 1.0, 0.0, 0.0, 0.0, 0.0], [0.0, 0.0, 0.0, 0.0, 0.0, 0.0], [0.0, 0.0, 1.0, 0.0, 0.0, 0.0], [0.0, 0.0, 0.0, 0.0, 0.0, 0.0], [0.0, 0.0, 0.0, 0.0, 1.0, 0.0]]}, {"times": {"old_time": 38, "new_time": 39}, "rewards": [3.6511539694533597], "actions": ["orange"], "densities": [2.0, 11.161196604729337, 0.0, 0.0, 0.0, 0.0], "lights": [[0.0, 0.0, 0.0, 0.0, 0.0, 0.0], [1.0, 0.30000000000000004, 0.0, 0.0, 0.0, 0.0], [0.0, 0.7, 0.0, 0.0, 0.0, 0.0], [0.0, 0.0, 1.0, 0.0, 0.0, 0.0], [0.0, 0.0, 0.0, 0.0, 0.0, 0.0], [0.0, 0.0, 0.0, 0.0, 1.0, 0.0]]}, {"times": {"old_time": 39, "new_time": 40}, "rewards": [2.269434081786861], "actions": [1], "densities": [2.0, 5.3483589814188015, 7.812837623310536, 0.0, 0.0, 0.0], "lights": [[0.0, 0.0, 0.0, 0.0, 0.0, 0.0], [1.0, 1.0, 0.0, 0.0, 0.0, 0.0], [0.0, 0.0, 0.0, 0.0, 0.0, 0.0], [0.0, 0.0, 1.0, 0.0, 0.0, 0.0], [0.0, 0.0, 0.0, 0.0, 0.0, 0.0], [0.0, 0.0, 0.0, 0.0, 1.0, 0.0]]}, {"times": {"old_time": 40, "new_time": 41}, "rewards": [4.458037939037663], "actions": ["orange"], "densities": [2.0, 7.3483589814188015, 0.0, 7.812837623310536, 0.0, 0.0], "lights": [[0.0, 0.0, 0.0, 0.0, 0.0, 0.0], [1.0, 1.0, 0.0, 0.0, 0.0, 0.0], [0.0, 0.0, 0.0, 0.0, 0.0, 0.0], [0.0, 0.0, 1.0, 0.0, 0.0, 0.0], [0.0, 0.0, 0.0, 0.0, 0.0, 0.0], [0.0, 0.0, 0.0, 0.0, 1.0, 0.0]]}, {"times": {"old_time": 41, "new_time": 42}, "rewards": [6.590060639113224], "actions": ["orange"], "densities": [2.0, 9.348358981418802, 0.0, 0.0, 0.0, 0.0], "lights": [[0.0, 0.0, 0.0, 0.0, 0.0, 0.0], [1.0, 0.7, 0.0, 0.0, 0.0, 0.0], [0.0, 0.0, 0.0, 0.0, 0.0, 0.0], [0.0, 0.0, 1.0, 0.0, 0.0, 0.0], [0.0, 0.3, 0.0, 0.0, 0.0, 0.0], [0.0, 0.0, 0.0, 0.0, 1.0, 0.0]]}, {"times": {"old_time": 42, "new_time": 43}, "rewards": [6.413042447379257], "actions": [0], "densities": [2.0, 8.54385128699316, 0.0, 0.0, 2.80450769442564, 0.0], "lights": [[0.0, 0.0, 0.0, 0.0, 0.0, 0.0], [1.0, 1.0, 0.0, 0.0, 0.0, 0.0], [0.0, 0.0, 0.0, 0.0, 0.0, 0.0], [0.0, 0.0, 1.0, 0.0, 0.0, 0.0], [0.0, 0.0, 0.0, 0.0, 0.0, 0.0], [0.0, 0.0, 0.0, 0.0, 1.0, 0.0]]}, {"times": {"old_time": 43, "new_time": 44}, "rewards": [4.224438590128455], "actions": ["orange"], "densities": [2.0, 10.54385128699316, 0.0, 0.0, 0.0, 2.80450769442564], "lights": [[0.0, 0.0, 0.0, 0.0, 0.0, 0.0], [1.0, 1.0, 0.0, 0.0, 0.0, 0.0], [0.0, 0.0, 0.0, 0.0, 0.0, 0.0], [0.0, 0.0, 1.0, 0.0, 0.0, 0.0], [0.0, 0.0, 0.0, 0.0, 0.0, 0.0], [0.0, 0.0, 0.0, 0.0, 1.0, 0.0]]}, {"times": {"old_time": 44, "new_time": 45}, "rewards": [2.092415890052893], "actions": ["orange"], "densities": [2.0, 12.54385128699316, 0.0, 0.0, 0.0, 0.0], "lights": [[0.0, 0.0, 0.0, 0.0, 0.0, 0.0], [1.0, 0.30000000000000004, 0.0, 0.0, 0.0, 0.0], [0.0, 0.7, 0.0, 0.0, 0.0, 0.0], [0.0, 0.0, 1.0, 0.0, 0.0, 0.0], [0.0, 0.0, 0.0, 0.0, 0.0, 0.0], [0.0, 0.0, 0.0, 0.0, 1.0, 0.0]]}, {"times": {"old_time": 45, "new_time": 46}, "rewards": [7.617612620419724], "actions": [1], "densities": [2.0, 5.7631553860979485, 8.78069590089521, 0.0, 0.0, 0.0], "lights": [[0.0, 0.0, 0.0, 0.0, 0.0, 0.0], [1.0, 1.0, 0.0, 0.0, 0.0, 0.0], [0.0, 0.0, 0.0, 0.0, 0.0, 0.0], [0.0, 0.0, 1.0, 0.0, 0.0, 0.0], [0.0, 0.0, 0.0, 0.0, 0.0, 0.0], [0.0, 0.0, 0.0, 0.0, 1.0, 0.0]]}, {"times": {"old_time": 46, "new_time": 47}, "rewards": [11.302896406545642], "actions": ["orange"], "densities": [2.0, 7.7631553860979485, 0.0, 8.78069590089521, 0.0, 0.0], "lights": [[0.0, 0.0, 0.0, 0.0, 0.0, 0.0], [1.0, 1.0, 0.0, 0.0, 0.0, 0.0], [0.0, 0.0, 0.0, 0.0, 0.0, 0.0], [0.0, 0.0, 1.0, 0.0, 0.0, 0.0], [0.0, 0.0, 0.0, 0.0, 0.0, 0.0], [0.0, 0.0, 0.0, 0.0, 1.0, 0.0]]}, {"times": {"old_time": 47, "new_time": 48}, "rewards": [11.302896406545642], "actions": ["orange"], "densities": [2.0, 9.76315538609795, 0.0, 0.0, 0.0, 0.0], "lights": [[0.0, 0.0, 0.0, 0.0, 0.0, 0.0], [1.0, 0.7, 0.0, 0.0, 0.0, 0.0], [0.0, 0.0, 0.0, 0.0, 0.0, 0.0], [0.0, 0.0, 1.0, 0.0, 0.0, 0.0], [0.0, 0.3, 0.0, 0.0, 0.0, 0.0], [0.0, 0.0, 0.0, 0.0, 1.0, 0.0]]}, {"times": {"old_time": 48, "new_time": 49}, "rewards": [3.6852837861259173], "actions": [1], "densities": [2.0, 8.834208770268564, 0.0, 0.0, 2.9289466158293846, 0.0], "lights": [[0.0, 0.0, 0.0, 0.0, 0.0, 0.0], [1.0, 0.7, 0.0, 0.0, 0.0, 0.0], [0.0, 0.0, 0.0, 0.0, 0.0, 0.0], [0.0, 0.0, 1.0, 0.0, 0.0, 0.0], [0.0, 0.3, 0.0, 0.0, 0.0, 0.0], [0.0, 0.0, 0.0, 0.0, 1.0, 0.0]]}, {"times": {"old_time": 49, "new_time": 50}, "rewards": [2.273822201073332], "actions": [0], "densities": [2.0, 8.183946139187995, 0.0, 0.0, 2.6502626310805693, 2.9289466158293846], "lights": [[0.0, 0.0, 0.0, 0.0, 0.0, 0.0], [1.0, 1.0, 0.0, 0.0, 0.0, 0.0], [0.0, 0.0, 0.0, 0.0, 0.0, 0.0], [0.0, 0.0, 1.0, 0.0, 0.0, 0.0], [0.0, 0.0, 0.0, 0.0, 0.0, 0.0], [0.0, 0.0, 0.0, 0.0, 1.0, 0.0]]}, {"times": {"old_time": 50, "new_time": 51}, "rewards": [2.273822201073332], "actions": ["orange"], "densities": [2.0, 10.183946139187995, 0.0, 0.0, 0.0, 2.6502626310805693], "lights": [[0.0, 0.0, 0.0, 0.0, 0.0, 0.0], [1.0, 1.0, 0.0, 0.0, 0.0, 0.0], [0.0, 0.0, 0.0, 0.0, 0.0, 0.0], [0.0, 0.0, 1.0, 0.0, 0.0, 0.0], [0.0, 0.0, 0.0, 0.0, 0.0, 0.0], [0.0, 0.0, 0.0, 0.0, 1.0, 0.0]]}, {"times": {"old_time": 51, "new_time": 52}, "rewards": [2.273822201073332], "actions": ["orange"], "densities": [2.0, 12.183946139187995, 0.0, 0.0, 0.0, 0.0], "lights": [[0.0, 0.0, 0.0, 0.0, 0.0, 0.0], [1.0, 0.30000000000000004, 0.0, 0.0, 0.0, 0.0], [0.0, 0.7, 0.0, 0.0, 0.0, 0.0], [0.0, 0.0, 1.0, 0.0, 0.0, 0.0], [0.0, 0.0, 0.0, 0.0, 0.0, 0.0], [0.0, 0.0, 0.0, 0.0, 1.0, 0.0]]}, {"times": {"old_time": 52, "new_time": 53}, "rewards": [7.913909595086443], "actions": [1], "densities": [2.0, 5.655183841756399, 8.528762297431596, 0.0, 0.0, 0.0], "lights": [[0.0, 0.0, 0.0, 0.0, 0.0, 0.0], [1.0, 1.0, 0.0, 0.0, 0.0, 0.0], [0.0, 0.0, 0.0, 0.0, 0.0, 0.0], [0.0, 0.0, 1.0, 0.0, 0.0, 0.0], [0.0, 0.0, 0.0, 0.0, 0.0, 0.0], [0.0, 0.0, 0.0, 0.0, 1.0, 0.0]]}, {"times": {"old_time": 53, "new_time": 54}, "rewards": [7.913909595086443], "actions": ["orange"], "densities": [2.0, 7.655183841756399, 0.0, 8.528762297431596, 0.0, 0.0], "lights": [[0.0, 0.0, 0.0, 0.0, 0.0, 0.0], [1.0, 1.0, 0.0, 0.0, 0.0, 0.0], [0.0, 0.0, 0.0, 0.0, 0.0, 0.0], [0.0, 0.0, 1.0, 0.0, 0.0, 0.0], [0.0, 0.0, 0.0, 0.0, 0.0, 0.0], [0.0, 0.0, 0.0, 0.0, 1.0, 0.0]]}, {"times": {"old_time": 54, "new_time": 55}, "rewards": [7.913909595086443], "actions": ["orange"], "densities": [2.0, 9.655183841756399, 0.0, 0.0, 0.0, 0.0], "lights": [[0.0, 0.0, 0.0, 0.0, 0.0, 0.0], [1.0, 0.7, 0.0, 0.0, 0.0, 0.0], [0.0, 0.0, 0.0, 0.0, 0.0, 0.0], [0.0, 0.0, 1.0, 0.0, 0.0, 0.0], [0.0, 0.3, 0.0, 0.0, 0.0, 0.0], [0.0, 0.0, 0.0, 0.0, 1.0, 0.0]]}, {"times": {"old_time": 55, "new_time": 56}, "rewards": [2.8175026622253996], "actions": [0], "densities": [2.0, 8.758628689229479, 0.0, 0.0, 2.8965551525269198, 0.0], "lights": [[0.0, 0.0, 0.0, 0.0, 0.0, 0.0], [1.0, 1.0, 0.0, 0.0, 0.0, 0.0], [0.0, 0.0, 0.0, 0.0, 0.0, 0.0], [0.0, 0.0, 1.0, 0.0, 0.0, 0.0], [0.0, 0.0, 0.0, 0.0, 0.0, 0.0], [0.0, 0.0, 0.0, 0.0, 1.0, 0.0]]}, {"times": {"old_time": 56, "new_time": 57}, "rewards": [5.389754525783179], "actions": ["orange"], "densities": [2.0, 10.758628689229479, 0.0, 0.0, 0.0, 2.8965551525269198], "lights": [[0.0, 0.0, 0.0, 0.0, 0.0, 0.0], [1.0, 1.0, 0.0, 0.0, 0.0, 0.0], [0.0, 0.0, 0.0, 0.0, 0.0, 0.0], [0.0, 0.0, 1.0, 0.0, 0.0, 0.0], [0.0, 0.0, 0.0, 0.0, 0.0, 0.0], [0.0, 0.0, 0.0, 0.0, 1.0, 0.0]]}, {"times": {"old_time": 57, "new_time": 58}, "rewards": [5.389754525783179], "actions": ["orange"], "densities": [2.0, 12.758628689229479, 0.0, 0.0, 0.0, 0.0], "lights": [[0.0, 0.0, 0.0, 0.0, 0.0, 0.0], [1.0, 0.30000000000000004, 0.0, 0.0, 0.0, 0.0], [0.0, 0.7, 0.0, 0.0, 0.0, 0.0], [0.0, 0.0, 1.0, 0.0, 0.0, 0.0], [0.0, 0.0, 0.0, 0.0, 0.0, 0.0], [0.0, 0.0, 0.0, 0.0, 1.0, 0.0]]}, {"times": {"old_time": 58, "new_time": 59}, "rewards": [2.5722518635577796], "actions": [0], "densities": [2.0, 5.827588606768844, 8.931040082460635, 0.0, 0.0, 0.0], "lights": [[0.0, 0.0, 0.0, 0.0, 0.0, 0.0], [1.0, 0.30000000000000004, 0.0, 0.0, 0.0, 0.0], [0.0, 0.7, 0.0, 0.0, 0.0, 0.0], [0.0, 0.0, 1.0, 0.0, 0.0, 0.0], [0.0, 0.0, 0.0, 0.0, 0.0, 0.0], [0.0, 0.0, 0.0, 0.0, 1.0, 0.0]]}, {"times": {"old_time": 59, "new_time": 60}, "rewards": [8.401344710477707], "actions": [1], "densities": [2.0, 3.7482765820306536, 4.07931202473819, 8.931040082460635, 0.0, 0.0], "lights": [[0.0, 0.0, 0.0, 0.0, 0.0, 0.0], [1.0, 1.0, 0.0, 0.0, 0.0, 0.0], [0.0, 0.0, 0.0, 0.0, 0.0, 0.0], [0.0, 0.0, 1.0, 0.0, 0.0, 0.0], [0.0, 0.0, 0.0, 0.0, 0.0, 0.0], [0.0, 0.0, 0.0, 0.0, 1.0, 0.0]]}, {"times": {"old_time": 60, "new_time": 61}, "rewards": [12.321748123621019], "actions": ["orange"], "densities": [2.0, 5.748276582030654, 0.0, 4.07931202473819, 0.0, 0.0], "lights": [[0.0, 0.0, 0.0, 0.0, 0.0, 0.0], [1.0, 1.0, 0.0, 0.0, 0.0, 0.0], [0.0, 0.0, 0.0, 0.0, 0.0, 0.0], [0.0, 0.0, 1.0, 0.0, 0.0, 0.0], [0.0, 0.0, 0.0, 0.0, 0.0, 0.0], [0.0, 0.0, 0.0, 0.0, 1.0, 0.0]]}, {"times": {"old_time": 61, "new_time": 62}, "rewards": [12.321748123621019], "actions": ["orange"], "densities": [2.0, 7.748276582030654, 0.0, 0.0, 0.0, 0.0], "lights": [[0.0, 0.0, 0.0, 0.0, 0.0, 0.0], [1.0, 0.7, 0.0, 0.0, 0.0, 0.0], [0.0, 0.0, 0.0, 0.0, 0.0, 0.0], [0.0, 0.0, 1.0, 0.0, 0.0, 0.0], [0.0, 0.3, 0.0, 0.0, 0.0, 0.0], [0.0, 0.0, 0.0, 0.0, 1.0, 0.0]]}, {"times": {"old_time": 62, "new_time": 63}, "rewards": [3.9204034131433123], "actions": [0], "densities": [2.0, 7.423793607421457, 0.0, 0.0, 2.324482974609196, 0.0], "lights": [[0.0, 0.0, 0.0, 0.0, 0.0, 0.0], [1.0, 1.0, 0.0, 0.0, 0.0, 0.0], [0.0, 0.0, 0.0, 0.0, 0.0, 0.0], [0.0, 0.0, 1.0, 0.0, 0.0, 0.0], [0.0, 0.0, 0.0, 0.0, 0.0, 0.0], [0.0, 0.0, 0.0, 0.0, 1.0, 0.0]]}, {"times": {"old_time": 63, "new_time": 64}, "rewards": [2.30405186740414], "actions": ["orange"], "densities": [2.0, 9.423793607421457, 0.0, 0.0, 0.0, 2.324482974609196], "lights": [[0.0, 0.0, 0.0, 0.0, 0.0, 0.0], [1.0, 1.0, 0.0, 0.0, 0.0, 0.0], [0.0, 0.0, 0.0, 0.0, 0.0, 0.0], [0.0, 0.0, 1.0, 0.0, 0.0, 0.0], [0.0, 0.0, 0.0, 0.0, 0.0, 0.0], [0.0, 0.0, 0.0, 0.0, 1.0, 0.0]]}, {"times": {"old_time": 64, "new_time": 65}, "rewards": [2.30405186740414], "actions": ["orange"], "densities": [2.0, 11.423793607421457, 0.0, 0.0, 0.0, 0.0], "lights": [[0.0, 0.0, 0.0, 0.0, 0.0, 0.0], [1.0, 0.30000000000000004, 0.0, 0.0, 0.0, 0.0], [0.0, 0.7, 0.0, 0.0, 0.0, 0.0], [0.0, 0.0, 1.0, 0.0, 0.0, 0.0], [0.0, 0.0, 0.0, 0.0, 0.0, 0.0], [0.0, 0.0, 0.0, 0.0, 1.0, 0.0]]}, {"times": {"old_time": 65, "new_time": 66}, "rewards": [2.30405186740414], "actions": [1], "densities": [2.0, 5.4271380822264375, 7.9966555251950195, 0.0, 0.0, 0.0], "lights": [[0.0, 0.0, 0.0, 0.0, 0.0, 0.0], [1.0, 1.0, 0.0, 0.0, 0.0, 0.0], [0.0, 0.0, 0.0, 0.0, 0.0, 0.0], [0.0, 0.0, 1.0, 0.0, 0.0, 0.0], [0.0, 0.0, 0.0, 0.0, 0.0, 0.0], [0.0, 0.0, 0.0, 0.0, 1.0, 0.0]]}, {"times": {"old_time": 66, "new_time": 67}, "rewards": [7.963284716760095], "actions": ["orange"], "densities": [2.0, 7.4271380822264375, 0.0, 7.9966555251950195, 0.0, 0.0], "lights": [[0.0, 0.0, 0.0, 0.0, 0.0, 0.0], [1.0, 1.0, 0.0, 0.0, 0.0, 0.0], [0.0, 0.0, 0.0, 0.0, 0.0, 0.0], [0.0, 0.0, 1.0, 0.0, 0.0, 0.0], [0.0, 0.0, 0.0, 0.0, 0.0, 0.0], [0.0, 0.0, 0.0, 0.0, 1.0, 0.0]]}, {"times": {"old_time": 67, "new_time": 68}, "rewards": [7.963284716760095], "actions": ["orange"], "densities": [2.0, 9.427138082226438, 0.0, 0.0, 0.0, 0.0], "lights": [[0.0, 0.0, 0.0, 0.0, 0.0, 0.0], [1.0, 0.7, 0.0, 0.0, 0.0, 0.0], [0.0, 0.0, 0.0, 0.0, 0.0, 0.0], [0.0, 0.0, 1.0, 0.0, 0.0, 0.0], [0.0, 0.3, 0.0, 0.0, 0.0, 0.0], [0.0, 0.0, 0.0, 0.0, 1.0, 0.0]]}, {"times": {"old_time": 68, "new_time": 69}, "rewards": [7.963284716760095], "actions": [0], "densities": [2.0, 8.598996657558507, 0.0, 0.0, 2.8281414246679315, 0.0], "lights": [[0.0, 0.0, 0.0, 0.0, 0.0, 0.0], [1.0, 1.0, 0.0, 0.0, 0.0, 0.0], [0.0, 0.0, 0.0, 0.0, 0.0, 0.0], [0.0, 0.0, 1.0, 0.0, 0.0, 0.0], [0.0, 0.0, 0.0, 0.0, 0.0, 0.0], [0.0, 0.0, 0.0, 0.0, 1.0, 0.0]]}, {"times": {"old_time": 69, "new_time": 70}, "rewards": [2.8238508921548693], "actions": ["orange"], "densities": [2.0, 10.598996657558507, 0.0, 0.0, 0.0, 2.8281414246679315], "lights": [[0.0, 0.0, 0.0, 0.0, 0.0, 0.0], [1.0, 1.0, 0.0, 0.0, 0.0, 0.0], [0.0, 0.0, 0.0, 0.0, 0.0, 0.0], [0.0, 0.0, 1.0, 0.0, 0.0, 0.0], [0.0, 0.0, 0.0, 0.0, 0.0, 0.0], [0.0, 0.0, 0.0, 0.0, 1.0, 0.0]]}, {"times": {"old_time": 70, "new_time": 71}, "rewards": [5.400546516663278], "actions": ["orange"], "densities": [2.0, 12.598996657558507, 0.0, 0.0, 0.0, 0.0], "lights": [[0.0, 0.0, 0.0, 0.0, 0.0, 0.0], [1.0, 0.30000000000000004, 0.0, 0.0, 0.0, 0.0], [0.0, 0.7, 0.0, 0.0, 0.0, 0.0], [0.0, 0.0, 1.0, 0.0, 0.0, 0.0], [0.0, 0.0, 0.0, 0.0, 0.0, 0.0], [0.0, 0.0, 0.0, 0.0, 1.0, 0.0]]}, {"times": {"old_time": 71, "new_time": 72}, "rewards": [7.804233453819163], "actions": [1], "densities": [2.0, 5.779698997267553, 8.819297660290955, 0.0, 0.0, 0.0], "lights": [[0.0, 0.0, 0.0, 0.0, 0.0, 0.0], [1.0, 1.0, 0.0, 0.0, 0.0, 0.0], [0.0, 0.0, 0.0, 0.0, 0.0, 0.0], [0.0, 0.0, 1.0, 0.0, 0.0, 0.0], [0.0, 0.0, 0.0, 0.0, 0.0, 0.0], [0.0, 0.0, 0.0, 0.0, 1.0, 0.0]]}, {"times": {"old_time": 72, "new_time": 73}, "rewards": [7.262963417673413], "actions": ["orange"], "densities": [2.0, 7.779698997267553, 0.0, 8.819297660290955, 0.0, 0.0], "lights": [[0.0, 0.0, 0.0, 0.0, 0.0, 0.0], [1.0, 1.0, 0.0, 0.0, 0.0, 0.0], [0.0, 0.0, 0.0, 0.0, 0.0, 0.0], [0.0, 0.0, 1.0, 0.0, 0.0, 0.0], [0.0, 0.0, 0.0, 0.0, 0.0, 0.0], [0.0, 0.0, 0.0, 0.0, 1.0, 0.0]]}, {"times": {"old_time": 73, "new_time": 74}, "rewards": [4.686267793165005], "actions": ["orange"], "densities": [2.0, 9.779698997267552, 0.0, 0.0, 0.0, 0.0], "lights": [[0.0, 0.0, 0.0, 0.0, 0.0, 0.0], [1.0, 0.7, 0.0, 0.0, 0.0, 0.0], [0.0, 0.0, 0.0, 0.0, 0.0, 0.0], [0.0, 0.0, 1.0, 0.0, 0.0, 0.0], [0.0, 0.3, 0.0, 0.0, 0.0, 0.0], [0.0, 0.0, 0.0, 0.0, 1.0, 0.0]]}, {"times": {"old_time": 74, "new_time": 75}, "rewards": [2.28258085600912], "actions": [0], "densities": [2.0, 8.845789298087286, 0.0, 0.0, 2.9339096991802656, 0.0], "lights": [[0.0, 0.0, 0.0, 0.0, 0.0, 0.0], [1.0, 1.0, 0.0, 0.0, 0.0, 0.0], [0.0, 0.0, 0.0, 0.0, 0.0, 0.0], [0.0, 0.0, 1.0, 0.0, 0.0, 0.0], [0.0, 0.0, 0.0, 0.0, 0.0, 0.0], [0.0, 0.0, 0.0, 0.0, 1.0, 0.0]]}, {"times": {"old_time": 75, "new_time": 76}, "rewards": [7.928215398148228], "actions": ["orange"], "densities": [2.0, 10.845789298087286, 0.0, 0.0, 0.0, 2.9339096991802656], "lights": [[0.0, 0.0, 0.0, 0.0, 0.0, 0.0], [1.0, 1.0, 0.0, 0.0, 0.0, 0.0], [0.0, 0.0, 0.0, 0.0, 0.0, 0.0], [0.0, 0.0, 1.0, 0.0, 0.0, 0.0], [0.0, 0.0, 0.0, 0.0, 0.0, 0.0], [0.0, 0.0, 0.0, 0.0, 1.0, 0.0]]}, {"times": {"old_time": 76, "new_time": 77}, "rewards": [7.928215398148228], "actions": ["orange"], "densities": [2.0, 12.845789298087286, 0.0, 0.0, 0.0, 0.0], "lights": [[0.0, 0.0, 0.0, 0.0, 0.0, 0.0], [1.0, 0.30000000000000004, 0.0, 0.0, 0.0, 0.0], [0.0, 0.7, 0.0, 0.0, 0.0, 0.0], [0.0, 0.0, 1.0, 0.0, 0.0, 0.0], [0.0, 0.0, 0.0, 0.0, 0.0, 0.0], [0.0, 0.0, 0.0, 0.0, 1.0, 0.0]]}, {"times": {"old_time": 77, "new_time": 78}, "rewards": [7.928215398148228], "actions": [1], "densities": [2.0, 5.853736789426186, 8.9920525086611, 0.0, 0.0, 0.0], "lights": [[0.0, 0.0, 0.0, 0.0, 0.0, 0.0], [1.0, 1.0, 0.0, 0.0, 0.0, 0.0], [0.0, 0.0, 0.0, 0.0, 0.0, 0.0], [0.0, 0.0, 1.0, 0.0, 0.0, 0.0], [0.0, 0.0, 0.0, 0.0, 0.0, 0.0], [0.0, 0.0, 0.0, 0.0, 1.0, 0.0]]}, {"times": {"old_time": 78, "new_time": 79}, "rewards": [2.819341979761915], "actions": ["orange"], "densities": [2.0, 7.853736789426186, 0.0, 8.9920525086611, 0.0, 0.0], "lights": [[0.0, 0.0, 0.0, 0.0, 0.0, 0.0], [1.0, 1.0, 0.0, 0.0, 0.0, 0.0], [0.0, 0.0, 0.0, 0.0, 0.0, 0.0], [0.0, 0.0, 1.0, 0.0, 0.0, 0.0], [0.0, 0.0, 0.0, 0.0, 0.0, 0.0], [0.0, 0.0, 0.0, 0.0, 1.0, 0.0]]}, {"times": {"old_time": 79, "new_time": 80}, "rewards": [5.3928813655952546], "actions": ["orange"], "densities": [2.0, 9.853736789426186, 0.0, 0.0, 0.0, 0.0], "lights": [[0.0, 0.0, 0.0, 0.0, 0.0, 0.0], [1.0, 0.7, 0.0, 0.0, 0.0, 0.0], [0.0, 0.0, 0.0, 0.0, 0.0, 0.0], [0.0, 0.0, 1.0, 0.0, 0.0, 0.0], [0.0, 0.3, 0.0, 0.0, 0.0, 0.0], [0.0, 0.0, 0.0, 0.0, 1.0, 0.0]]}, {"times": {"old_time": 80, "new_time": 81}, "rewards": [5.3928813655952546], "actions": [0], "densities": [2.0, 8.89761575259833, 0.0, 0.0, 2.956121036827856, 0.0], "lights": [[0.0, 0.0, 0.0, 0.0, 0.0, 0.0], [1.0, 1.0, 0.0, 0.0, 0.0, 0.0], [0.0, 0.0, 0.0, 0.0, 0.0, 0.0], [0.0, 0.0, 1.0, 0.0, 0.0, 0.0], [0.0, 0.0, 0.0, 0.0, 0.0, 0.0], [0.0, 0.0, 0.0, 0.0, 1.0, 0.0]]}, {"times": {"old_time": 81, "new_time": 82}, "rewards": [2.57353938583334], "actions": ["orange"], "densities": [2.0, 10.89761575259833, 0.0, 0.0, 0.0, 2.956121036827856], "lights": [[0.0, 0.0, 0.0, 0.0, 0.0, 0.0], [1.0, 1.0, 0.0, 0.0, 0.0, 0.0], [0.0, 0.0, 0.0, 0.0, 0.0, 0.0], [0.0, 0.0, 1.0, 0.0, 0.0, 0.0], [0.0, 0.0, 0.0, 0.0, 0.0, 0.0], [0.0, 0.0, 0.0, 0.0, 1.0, 0.0]]}, {"times": {"old_time": 82, "new_time": 83}, "rewards": [8.403447663527789], "actions": ["orange"], "densities": [2.0, 12.89761575259833, 0.0, 0.0, 0.0, 0.0], "lights": [[0.0, 0.0, 0.0, 0.0, 0.0, 0.0], [1.0, 0.30000000000000004, 0.0, 0.0, 0.0, 0.0], [0.0, 0.7, 0.0, 0.0, 0.0, 0.0], [0.0, 0.0, 1.0, 0.0, 0.0, 0.0], [0.0, 0.0, 0.0, 0.0, 0.0, 0.0], [0.0, 0.0, 0.0, 0.0, 1.0, 0.0]]}, {"times": {"old_time": 83, "new_time": 84}, "rewards": [8.403447663527789], "actions": [1], "densities": [2.0, 5.869284725779499, 9.028331026818831, 0.0, 0.0, 0.0], "lights": [[0.0, 0.0, 0.0, 0.0, 0.0, 0.0], [1.0, 1.0, 0.0, 0.0, 0.0, 0.0], [0.0, 0.0, 0.0, 0.0, 0.0, 0.0], [0.0, 0.0, 1.0, 0.0, 0.0, 0.0], [0.0, 0.0, 0.0, 0.0, 0.0, 0.0], [0.0, 0.0, 0.0, 0.0, 1.0, 0.0]]}, {"times": {"old_time": 84, "new_time": 85}, "rewards": [8.403447663527789], "actions": ["orange"], "densities": [2.0, 7.869284725779499, 0.0, 9.028331026818831, 0.0, 0.0], "lights": [[0.0, 0.0, 0.0, 0.0, 0.0, 0.0], [1.0, 1.0, 0.0, 0.0, 0.0, 0.0], [0.0, 0.0, 0.0, 0.0, 0.0, 0.0], [0.0, 0.0, 1.0, 0.0, 0.0, 0.0], [0.0, 0.0, 0.0, 0.0, 0.0, 0.0], [0.0, 0.0, 0.0, 0.0, 1.0, 0.0]]}, {"times": {"old_time": 85, "new_time": 86}, "rewards": [2.8804432710250016], "actions": ["orange"], "densities": [2.0, 9.8692847257795, 0.0, 0.0, 0.0, 0.0], "lights": [[0.0, 0.0, 0.0, 0.0, 0.0, 0.0], [1.0, 0.7, 0.0, 0.0, 0.0, 0.0], [0.0, 0.0, 0.0, 0.0, 0.0, 0.0], [0.0, 0.0, 1.0, 0.0, 0.0, 0.0], [0.0, 0.3, 0.0, 0.0, 0.0, 0.0], [0.0, 0.0, 0.0, 0.0, 1.0, 0.0]]}, {"times": {"old_time": 86, "new_time": 87}, "rewards": [2.8804432710250016], "actions": [0], "densities": [2.0, 8.908499308045648, 0.0, 0.0, 2.9607854177338497, 0.0], "lights": [[0.0, 0.0, 0.0, 0.0, 0.0, 0.0], [1.0, 1.0, 0.0, 0.0, 0.0, 0.0], [0.0, 0.0, 0.0, 0.0, 0.0, 0.0], [0.0, 0.0, 1.0, 0.0, 0.0, 0.0], [0.0, 0.0, 0.0, 0.0, 0.0, 0.0], [0.0, 0.0, 0.0, 0.0, 1.0, 0.0]]}, {"times": {"old_time": 87, "new_time": 88}, "rewards": [2.8804432710250016], "actions": ["orange"], "densities": [2.0, 10.908499308045648, 0.0, 0.0, 0.0, 2.9607854177338497], "lights": [[0.0, 0.0, 0.0, 0.0, 0.0, 0.0], [1.0, 1.0, 0.0, 0.0, 0.0, 0.0], [0.0, 0.0, 0.0, 0.0, 0.0, 0.0], [0.0, 0.0, 1.0, 0.0, 0.0, 0.0], [0.0, 0.0, 0.0, 0.0, 0.0, 0.0], [0.0, 0.0, 0.0, 0.0, 1.0, 0.0]]}, {"times": {"old_time": 88, "new_time": 89}, "rewards": [0.0], "actions": ["orange"], "densities": [2.0, 12.908499308045648, 0.0, 0.0, 0.0, 0.0], "lights": [[0.0, 0.0, 0.0, 0.0, 0.0, 0.0], [1.0, 0.30000000000000004, 0.0, 0.0, 0.0, 0.0], [0.0, 0.7, 0.0, 0.0, 0.0, 0.0], [0.0, 0.0, 1.0, 0.0, 0.0, 0.0], [0.0, 0.0, 0.0, 0.0, 0.0, 0.0], [0.0, 0.0, 0.0, 0.0, 1.0, 0.0]]}, {"times": {"old_time": 89, "new_time": 90}, "rewards": [0.0], "actions": [1], "densities": [2.0, 5.872549792413695, 9.035949515631954, 0.0, 0.0, 0.0], "lights": [[0.0, 0.0, 0.0, 0.0, 0.0, 0.0], [1.0, 1.0, 0.0, 0.0, 0.0, 0.0], [0.0, 0.0, 0.0, 0.0, 0.0, 0.0], [0.0, 0.0, 1.0, 0.0, 0.0, 0.0], [0.0, 0.0, 0.0, 0.0, 0.0, 0.0], [0.0, 0.0, 0.0, 0.0, 1.0, 0.0]]}, {"times": {"old_time": 89, "new_time": 90}, "rewards": [0], "actions": [1], "densities": [2.0, 5.872549792413695, 9.035949515631954, 0.0, 0.0, 0.0], "lights": [[0.0, 0.0, 0.0, 0.0, 0.0, 0.0], [1.0, 1.0, 0.0, 0.0, 0.0, 0.0], [0.0, 0.0, 0.0, 0.0, 0.0, 0.0], [0.0, 0.0, 1.0, 0.0, 0.0, 0.0], [0.0, 0.0, 0.0, 0.0, 0.0, 0.0], [0.0, 0.0, 0.0, 0.0, 1.0, 0.0]]}], "netName": "net11", "densityName": "random_28"}