{"learningMethod": "DQN", "learningEpochs": 0, "nets": [{"times": {"old_time": 0, "new_time": 1}, "rewards": [2.8], "actions": ["orange"], "densities": [0, 0, 0], "lights": [[1.0, 0.0, 0.0], [0.0, 0.0, 0.0], [0.0, 0.0, 0.0]]}, {"times": {"old_time": 1, "new_time": 2}, "rewards": [2.8], "actions": ["orange"], "densities": [2.0, 0.0, 0.0], "lights": [[0.30000000000000004, 0.0, 0.0], [0.0, 0.0, 0.0], [0.7, 0.0, 0.0]]}, {"times": {"old_time": 2, "new_time": 3}, "rewards": [2.8], "actions": [0], "densities": [2.6, 0.0, 1.4], "lights": [[1.0, 0.0, 0.0], [0.0, 0.0, 0.0], [0.0, 0.0, 0.0]]}, {"times": {"old_time": 3, "new_time": 4}, "rewards": [2.16], "actions": ["orange"], "densities": [4.6, 0.0, 0.0], "lights": [[1.0, 0.0, 0.0], [0.0, 0.0, 0.0], [0.0, 0.0, 0.0]]}, {"times": {"old_time": 4, "new_time": 5}, "rewards": [2.16], "actions": ["orange"], "densities": [6.6, 0.0, 0.0], "lights": [[0.7, 0.0, 0.0], [0.3, 0.0, 0.0], [0.0, 0.0, 0.0]]}, {"times": {"old_time": 5, "new_time": 6}, "rewards": [2.16], "actions": [0], "densities": [6.619999999999999, 1.9799999999999998, 0.0], "lights": [[0.7, 0.0, 0.0], [0.3, 0.0, 0.0], [0.0, 0.0, 0.0]]}, {"times": {"old_time": 6, "new_time": 7}, "rewards": [7.727999999999999], "actions": [0], "densities": [6.6339999999999995, 1.9859999999999998, 0.0], "lights": [[0.7, 0.0, 0.0], [0.3, 0.0, 0.0], [0.0, 0.0, 0.0]]}, {"times": {"old_time": 7, "new_time": 8}, "rewards": [7.727999999999999], "actions": [1], "densities": [6.6438, 1.9901999999999997, 0.0], "lights": [[1.0, 0.0, 0.0], [0.0, 0.0, 0.0], [0.0, 0.0, 0.0]]}, {"times": {"old_time": 8, "new_time": 9}, "rewards": [7.727999999999999], "actions": ["orange"], "densities": [8.643799999999999, 0.0, 0.0], "lights": [[1.0, 0.0, 0.0], [0.0, 0.0, 0.0], [0.0, 0.0, 0.0]]}, {"times": {"old_time": 9, "new_time": 10}, "rewards": [2.7936], "actions": ["orange"], "densities": [10.643799999999999, 0.0, 0.0], "lights": [[0.30000000000000004, 0.0, 0.0], [0.0, 0.0, 0.0], [0.7, 0.0, 0.0]]}, {"times": {"old_time": 10, "new_time": 11}, "rewards": [2.7936], "actions": [1], "densities": [5.19314, 0.0, 7.450659999999998], "lights": [[0.30000000000000004, 0.0, 0.0], [0.0, 0.0, 0.0], [0.7, 0.0, 0.0]]}, {"times": {"old_time": 11, "new_time": 12}, "rewards": [2.7936], "actions": [0], "densities": [3.557942, 0.0, 3.6351979999999995], "lights": [[1.0, 0.0, 0.0], [0.0, 0.0, 0.0], [0.0, 0.0, 0.0]]}, {"times": {"old_time": 12, "new_time": 13}, "rewards": [8.76288], "actions": ["orange"], "densities": [5.557942000000001, 0.0, 0.0], "lights": [[1.0, 0.0, 0.0], [0.0, 0.0, 0.0], [0.0, 0.0, 0.0]]}, {"times": {"old_time": 13, "new_time": 14}, "rewards": [12.791744], "actions": ["orange"], "densities": [7.557942000000001, 0.0, 0.0], "lights": [[0.7, 0.0, 0.0], [0.3, 0.0, 0.0], [0.0, 0.0, 0.0]]}, {"times": {"old_time": 14, "new_time": 15}, "rewards": [15.4004032], "actions": [0], "densities": [7.2905594, 2.2673826, 0.0], "lights": [[0.7, 0.0, 0.0], [0.3, 0.0, 0.0], [0.0, 0.0, 0.0]]}, {"times": {"old_time": 15, "new_time": 16}, "rewards": [8.82012096], "actions": [1], "densities": [7.10339158, 2.18716782, 0.0], "lights": [[1.0, 0.0, 0.0], [0.0, 0.0, 0.0], [0.0, 0.0, 0.0]]}, {"times": {"old_time": 16, "new_time": 17}, "rewards": [6.8460362880000005], "actions": ["orange"], "densities": [9.10339158, 0.0, 0.0], "lights": [[1.0, 0.0, 0.0], [0.0, 0.0, 0.0], [0.0, 0.0, 0.0]]}, {"times": {"old_time": 17, "new_time": 18}, "rewards": [6.2538108864], "actions": ["orange"], "densities": [11.10339158, 0.0, 0.0], "lights": [[0.30000000000000004, 0.0, 0.0], [0.0, 0.0, 0.0], [0.7, 0.0, 0.0]]}, {"times": {"old_time": 18, "new_time": 19}, "rewards": [4.0712131264], "actions": [1], "densities": [5.331017474000001, 0.0, 7.772374106], "lights": [[0.30000000000000004, 0.0, 0.0], [0.0, 0.0, 0.0], [0.7, 0.0, 0.0]]}, {"times": {"old_time": 19, "new_time": 20}, "rewards": [2.0164337984], "actions": [0], "densities": [3.5993052422000007, 0.0, 3.7317122318000004], "lights": [[1.0, 0.0, 0.0], [0.0, 0.0, 0.0], [0.0, 0.0, 0.0]]}, {"times": {"old_time": 20, "new_time": 21}, "rewards": [2.05925577408], "actions": ["orange"], "densities": [5.599305242200001, 0.0, 0.0], "lights": [[1.0, 0.0, 0.0], [0.0, 0.0, 0.0], [0.0, 0.0, 0.0]]}, {"times": {"old_time": 21, "new_time": 22}, "rewards": [2.05925577408], "actions": ["orange"], "densities": [7.599305242200001, 0.0, 0.0], "lights": [[0.7, 0.0, 0.0], [0.3, 0.0, 0.0], [0.0, 0.0, 0.0]]}, {"times": {"old_time": 22, "new_time": 23}, "rewards": [2.05925577408], "actions": [0], "densities": [7.31951366954, 2.27979157266, 0.0], "lights": [[0.7, 0.0, 0.0], [0.3, 0.0, 0.0], [0.0, 0.0, 0.0]]}, {"times": {"old_time": 23, "new_time": 24}, "rewards": [7.563451097663999], "actions": [0], "densities": [7.123659568678, 2.195854100862, 0.0], "lights": [[0.7, 0.0, 0.0], [0.3, 0.0, 0.0], [0.0, 0.0, 0.0]]}, {"times": {"old_time": 24, "new_time": 25}, "rewards": [7.563451097663999], "actions": [1], "densities": [6.9865616980746, 2.1370978706034, 0.0], "lights": [[1.0, 0.0, 0.0], [0.0, 0.0, 0.0], [0.0, 0.0, 0.0]]}, {"times": {"old_time": 25, "new_time": 26}, "rewards": [7.563451097663999], "actions": ["orange"], "densities": [8.986561698074599, 0.0, 0.0], "lights": [[1.0, 0.0, 0.0], [0.0, 0.0, 0.0], [0.0, 0.0, 0.0]]}, {"times": {"old_time": 26, "new_time": 27}, "rewards": [2.7724437125567998], "actions": ["orange"], "densities": [10.986561698074599, 0.0, 0.0], "lights": [[0.30000000000000004, 0.0, 0.0], [0.0, 0.0, 0.0], [0.7, 0.0, 0.0]]}, {"times": {"old_time": 27, "new_time": 28}, "rewards": [5.31315431134656], "actions": [1], "densities": [5.29596850942238, 0.0, 7.690593188652219], "lights": [[0.30000000000000004, 0.0, 0.0], [0.0, 0.0, 0.0], [0.7, 0.0, 0.0]]}, {"times": {"old_time": 28, "new_time": 29}, "rewards": [7.691651730499391], "actions": [1], "densities": [3.5887905528267146, 0.0, 3.707177956595666], "lights": [[0.30000000000000004, 0.0, 0.0], [0.0, 0.0, 0.0], [0.7, 0.0, 0.0]]}, {"times": {"old_time": 29, "new_time": 30}, "rewards": [4.919208017942592], "actions": [0], "densities": [3.0766371658480143, 0.0, 2.5121533869787], "lights": [[1.0, 0.0, 0.0], [0.0, 0.0, 0.0], [0.0, 0.0, 0.0]]}, {"times": {"old_time": 30, "new_time": 31}, "rewards": [2.378497419152832], "actions": ["orange"], "densities": [5.076637165848014, 0.0, 0.0], "lights": [[1.0, 0.0, 0.0], [0.0, 0.0, 0.0], [0.0, 0.0, 0.0]]}, {"times": {"old_time": 31, "new_time": 32}, "rewards": [8.084879117949626], "actions": ["orange"], "densities": [7.076637165848014, 0.0, 0.0], "lights": [[0.7, 0.0, 0.0], [0.3, 0.0, 0.0], [0.0, 0.0, 0.0]]}, {"times": {"old_time": 32, "new_time": 33}, "rewards": [11.910342853334514], "actions": [1], "densities": [6.95364601609361, 2.1229911497544043, 0.0], "lights": [[1.0, 0.0, 0.0], [0.0, 0.0, 0.0], [0.0, 0.0, 0.0]]}, {"times": {"old_time": 33, "new_time": 34}, "rewards": [11.910342853334514], "actions": ["orange"], "densities": [8.95364601609361, 0.0, 0.0], "lights": [[1.0, 0.0, 0.0], [0.0, 0.0, 0.0], [0.0, 0.0, 0.0]]}, {"times": {"old_time": 34, "new_time": 35}, "rewards": [3.8254637353848877], "actions": ["orange"], "densities": [10.95364601609361, 0.0, 0.0], "lights": [[0.30000000000000004, 0.0, 0.0], [0.0, 0.0, 0.0], [0.7, 0.0, 0.0]]}, {"times": {"old_time": 35, "new_time": 36}, "rewards": [2.2918453374066283], "actions": [1], "densities": [5.286093804828084, 0.0, 7.667552211265527], "lights": [[0.30000000000000004, 0.0, 0.0], [0.0, 0.0, 0.0], [0.7, 0.0, 0.0]]}, {"times": {"old_time": 36, "new_time": 37}, "rewards": [4.496137073591268], "actions": [1], "densities": [3.5858281414484257, 0.0, 3.7002656633796587], "lights": [[0.30000000000000004, 0.0, 0.0], [0.0, 0.0, 0.0], [0.7, 0.0, 0.0]]}, {"times": {"old_time": 37, "new_time": 38}, "rewards": [4.496137073591268], "actions": [0], "densities": [3.075748442434528, 0.0, 2.5100796990138976], "lights": [[1.0, 0.0, 0.0], [0.0, 0.0, 0.0], [0.0, 0.0, 0.0]]}, {"times": {"old_time": 38, "new_time": 39}, "rewards": [2.20429173618464], "actions": ["orange"], "densities": [5.075748442434528, 0.0, 0.0], "lights": [[1.0, 0.0, 0.0], [0.0, 0.0, 0.0], [0.0, 0.0, 0.0]]}, {"times": {"old_time": 39, "new_time": 40}, "rewards": [7.800343169101577], "actions": ["orange"], "densities": [7.075748442434528, 0.0, 0.0], "lights": [[0.7, 0.0, 0.0], [0.3, 0.0, 0.0], [0.0, 0.0, 0.0]]}, {"times": {"old_time": 40, "new_time": 41}, "rewards": [11.540446119832051], "actions": [0], "densities": [6.95302390970417, 2.1227245327303583, 0.0], "lights": [[0.7, 0.0, 0.0], [0.3, 0.0, 0.0], [0.0, 0.0, 0.0]]}, {"times": {"old_time": 41, "new_time": 42}, "rewards": [14.062477005051193], "actions": [1], "densities": [6.8671167367929185, 2.085907172911251, 0.0], "lights": [[1.0, 0.0, 0.0], [0.0, 0.0, 0.0], [0.0, 0.0, 0.0]]}, {"times": {"old_time": 42, "new_time": 43}, "rewards": [8.418743101515359], "actions": ["orange"], "densities": [8.86711673679292, 0.0, 0.0], "lights": [[1.0, 0.0, 0.0], [0.0, 0.0, 0.0], [0.0, 0.0, 0.0]]}, {"times": {"old_time": 43, "new_time": 44}, "rewards": [4.678640150784885], "actions": ["orange"], "densities": [10.86711673679292, 0.0, 0.0], "lights": [[0.30000000000000004, 0.0, 0.0], [0.0, 0.0, 0.0], [0.7, 0.0, 0.0]]}, {"times": {"old_time": 44, "new_time": 45}, "rewards": [2.1566092655657427], "actions": [0], "densities": [5.260135021037876, 0.0, 7.606981715755043], "lights": [[1.0, 0.0, 0.0], [0.0, 0.0, 0.0], [0.0, 0.0, 0.0]]}, {"times": {"old_time": 45, "new_time": 46}, "rewards": [2.0772783341441667], "actions": ["orange"], "densities": [7.260135021037876, 0.0, 0.0], "lights": [[1.0, 0.0, 0.0], [0.0, 0.0, 0.0], [0.0, 0.0, 0.0]]}, {"times": {"old_time": 46, "new_time": 47}, "rewards": [2.0772783341441667], "actions": ["orange"], "densities": [9.260135021037875, 0.0, 0.0], "lights": [[0.7, 0.0, 0.0], [0.3, 0.0, 0.0], [0.0, 0.0, 0.0]]}, {"times": {"old_time": 47, "new_time": 48}, "rewards": [2.0772783341441667], "actions": [0], "densities": [8.482094514726512, 2.7780405063113625, 0.0], "lights": [[0.7, 0.0, 0.0], [0.3, 0.0, 0.0], [0.0, 0.0, 0.0]]}, {"times": {"old_time": 48, "new_time": 49}, "rewards": [7.592887945768806], "actions": [0], "densities": [7.937466160308558, 2.5446283544179535, 0.0], "lights": [[0.7, 0.0, 0.0], [0.3, 0.0, 0.0], [0.0, 0.0, 0.0]]}, {"times": {"old_time": 49, "new_time": 50}, "rewards": [7.592887945768806], "actions": [1], "densities": [7.5562263122159905, 2.381239848092567, 0.0], "lights": [[1.0, 0.0, 0.0], [0.0, 0.0, 0.0], [0.0, 0.0, 0.0]]}, {"times": {"old_time": 50, "new_time": 51}, "rewards": [7.592887945768806], "actions": ["orange"], "densities": [9.55622631221599, 0.0, 0.0], "lights": [[1.0, 0.0, 0.0], [0.0, 0.0, 0.0], [0.0, 0.0, 0.0]]}, {"times": {"old_time": 51, "new_time": 52}, "rewards": [2.7762284501702754], "actions": ["orange"], "densities": [11.55622631221599, 0.0, 0.0], "lights": [[0.30000000000000004, 0.0, 0.0], [0.0, 0.0, 0.0], [0.7, 0.0, 0.0]]}, {"times": {"old_time": 52, "new_time": 53}, "rewards": [2.7762284501702754], "actions": [0], "densities": [5.466867893664798, 0.0, 8.089358418551193], "lights": [[1.0, 0.0, 0.0], [0.0, 0.0, 0.0], [0.0, 0.0, 0.0]]}, {"times": {"old_time": 53, "new_time": 54}, "rewards": [2.7762284501702754], "actions": ["orange"], "densities": [7.466867893664798, 0.0, 0.0], "lights": [[1.0, 0.0, 0.0], [0.0, 0.0, 0.0], [0.0, 0.0, 0.0]]}, {"times": {"old_time": 54, "new_time": 55}, "rewards": [8.73450646861145], "actions": ["orange"], "densities": [9.466867893664798, 0.0, 0.0], "lights": [[0.7, 0.0, 0.0], [0.3, 0.0, 0.0], [0.0, 0.0, 0.0]]}, {"times": {"old_time": 55, "new_time": 56}, "rewards": [12.754858409194885], "actions": [1], "densities": [8.626807525565358, 2.840060368099439, 0.0], "lights": [[1.0, 0.0, 0.0], [0.0, 0.0, 0.0], [0.0, 0.0, 0.0]]}, {"times": {"old_time": 56, "new_time": 57}, "rewards": [12.754858409194885], "actions": ["orange"], "densities": [10.626807525565358, 0.0, 0.0], "lights": [[1.0, 0.0, 0.0], [0.0, 0.0, 0.0], [0.0, 0.0, 0.0]]}, {"times": {"old_time": 57, "new_time": 58}, "rewards": [4.020351940583435], "actions": ["orange"], "densities": [12.626807525565358, 0.0, 0.0], "lights": [[0.30000000000000004, 0.0, 0.0], [0.0, 0.0, 0.0], [0.7, 0.0, 0.0]]}, {"times": {"old_time": 58, "new_time": 59}, "rewards": [2.3169023923607273], "actions": [1], "densities": [5.788042257669607, 0.0, 8.83876526789575], "lights": [[0.30000000000000004, 0.0, 0.0], [0.0, 0.0, 0.0], [0.7, 0.0, 0.0]]}, {"times": {"old_time": 59, "new_time": 60}, "rewards": [4.538734067013236], "actions": [0], "densities": [3.7364126773008826, 0.0, 4.051629580368725], "lights": [[1.0, 0.0, 0.0], [0.0, 0.0, 0.0], [0.0, 0.0, 0.0]]}, {"times": {"old_time": 60, "new_time": 61}, "rewards": [4.538734067013236], "actions": ["orange"], "densities": [5.736412677300883, 0.0, 0.0], "lights": [[1.0, 0.0, 0.0], [0.0, 0.0, 0.0], [0.0, 0.0, 0.0]]}, {"times": {"old_time": 61, "new_time": 62}, "rewards": [2.221831674652509], "actions": ["orange"], "densities": [7.736412677300883, 0.0, 0.0], "lights": [[0.7, 0.0, 0.0], [0.3, 0.0, 0.0], [0.0, 0.0, 0.0]]}, {"times": {"old_time": 62, "new_time": 63}, "rewards": [7.828991735265764], "actions": [1], "densities": [7.4154888741106175, 2.3209238031902646, 0.0], "lights": [[1.0, 0.0, 0.0], [0.0, 0.0, 0.0], [0.0, 0.0, 0.0]]}, {"times": {"old_time": 63, "new_time": 64}, "rewards": [7.828991735265764], "actions": ["orange"], "densities": [9.415488874110618, 0.0, 0.0], "lights": [[1.0, 0.0, 0.0], [0.0, 0.0, 0.0], [0.0, 0.0, 0.0]]}, {"times": {"old_time": 64, "new_time": 65}, "rewards": [7.828991735265764], "actions": ["orange"], "densities": [11.415488874110618, 0.0, 0.0], "lights": [[0.30000000000000004, 0.0, 0.0], [0.0, 0.0, 0.0], [0.7, 0.0, 0.0]]}, {"times": {"old_time": 65, "new_time": 66}, "rewards": [2.806584651677027], "actions": [1], "densities": [5.424646662233187, 0.0, 7.990842211877433], "lights": [[0.30000000000000004, 0.0, 0.0], [0.0, 0.0, 0.0], [0.7, 0.0, 0.0]]}, {"times": {"old_time": 66, "new_time": 67}, "rewards": [5.371193907850946], "actions": [0], "densities": [3.627393998669956, 0.0, 3.7972526635632304], "lights": [[1.0, 0.0, 0.0], [0.0, 0.0, 0.0], [0.0, 0.0, 0.0]]}, {"times": {"old_time": 67, "new_time": 68}, "rewards": [7.766420387172689], "actions": ["orange"], "densities": [5.627393998669956, 0.0, 0.0], "lights": [[1.0, 0.0, 0.0], [0.0, 0.0, 0.0], [0.0, 0.0, 0.0]]}, {"times": {"old_time": 68, "new_time": 69}, "rewards": [7.236494271020881], "actions": ["orange"], "densities": [7.627393998669956, 0.0, 0.0], "lights": [[0.7, 0.0, 0.0], [0.3, 0.0, 0.0], [0.0, 0.0, 0.0]]}, {"times": {"old_time": 69, "new_time": 70}, "rewards": [6.865545989714617], "actions": [1], "densities": [7.339175799068969, 2.288218199600987, 0.0], "lights": [[1.0, 0.0, 0.0], [0.0, 0.0, 0.0], [0.0, 0.0, 0.0]]}, {"times": {"old_time": 70, "new_time": 71}, "rewards": [4.470319510392875], "actions": ["orange"], "densities": [9.339175799068968, 0.0, 0.0], "lights": [[1.0, 0.0, 0.0], [0.0, 0.0, 0.0], [0.0, 0.0, 0.0]]}, {"times": {"old_time": 71, "new_time": 72}, "rewards": [2.193660974867654], "actions": ["orange"], "densities": [11.339175799068968, 0.0, 0.0], "lights": [[0.30000000000000004, 0.0, 0.0], [0.0, 0.0, 0.0], [0.7, 0.0, 0.0]]}, {"times": {"old_time": 72, "new_time": 73}, "rewards": [7.782979592283834], "actions": [0], "densities": [5.401752739720691, 0.0, 7.937423059348277], "lights": [[1.0, 0.0, 0.0], [0.0, 0.0, 0.0], [0.0, 0.0, 0.0]]}, {"times": {"old_time": 73, "new_time": 74}, "rewards": [11.517873469968984], "actions": ["orange"], "densities": [7.401752739720691, 0.0, 0.0], "lights": [[1.0, 0.0, 0.0], [0.0, 0.0, 0.0], [0.0, 0.0, 0.0]]}, {"times": {"old_time": 74, "new_time": 75}, "rewards": [14.03834163327453], "actions": ["orange"], "densities": [9.401752739720692, 0.0, 0.0], "lights": [[0.7, 0.0, 0.0], [0.3, 0.0, 0.0], [0.0, 0.0, 0.0]]}, {"times": {"old_time": 75, "new_time": 76}, "rewards": [6.255362040990696], "actions": [1], "densities": [8.581226917804484, 2.8205258219162075, 0.0], "lights": [[1.0, 0.0, 0.0], [0.0, 0.0, 0.0], [0.0, 0.0, 0.0]]}, {"times": {"old_time": 76, "new_time": 77}, "rewards": [2.5204681633055452], "actions": ["orange"], "densities": [10.581226917804484, 0.0, 0.0], "lights": [[1.0, 0.0, 0.0], [0.0, 0.0, 0.0], [0.0, 0.0, 0.0]]}, {"times": {"old_time": 77, "new_time": 78}, "rewards": [2.1240601924249987], "actions": ["orange"], "densities": [12.581226917804484, 0.0, 0.0], "lights": [[0.30000000000000004, 0.0, 0.0], [0.0, 0.0, 0.0], [0.7, 0.0, 0.0]]}, {"times": {"old_time": 78, "new_time": 79}, "rewards": [4.210902327122498], "actions": [1], "densities": [5.7743680753413456, 0.0, 8.806858842463138], "lights": [[0.30000000000000004, 0.0, 0.0], [0.0, 0.0, 0.0], [0.7, 0.0, 0.0]]}, {"times": {"old_time": 79, "new_time": 80}, "rewards": [4.210902327122498], "actions": [1], "densities": [3.7323104226024038, 0.0, 4.042057652738942], "lights": [[0.30000000000000004, 0.0, 0.0], [0.0, 0.0, 0.0], [0.7, 0.0, 0.0]]}, {"times": {"old_time": 80, "new_time": 81}, "rewards": [2.0868421346974992], "actions": [1], "densities": [3.1196931267807213, 0.0, 2.6126172958216825], "lights": [[0.30000000000000004, 0.0, 0.0], [0.0, 0.0, 0.0], [0.7, 0.0, 0.0]]}, {"times": {"old_time": 81, "new_time": 82}, "rewards": [7.608508820005914], "actions": [0], "densities": [2.935907938034217, 0.0, 2.183785188746505], "lights": [[1.0, 0.0, 0.0], [0.0, 0.0, 0.0], [0.0, 0.0, 0.0]]}, {"times": {"old_time": 82, "new_time": 83}, "rewards": [11.29106146600769], "actions": ["orange"], "densities": [4.935907938034217, 0.0, 0.0], "lights": [[1.0, 0.0, 0.0], [0.0, 0.0, 0.0], [0.0, 0.0, 0.0]]}, {"times": {"old_time": 83, "new_time": 84}, "rewards": [11.29106146600769], "actions": ["orange"], "densities": [6.935907938034217, 0.0, 0.0], "lights": [[0.7, 0.0, 0.0], [0.3, 0.0, 0.0], [0.0, 0.0, 0.0]]}, {"times": {"old_time": 84, "new_time": 85}, "rewards": [3.682552646001775], "actions": [0], "densities": [6.855135556623951, 2.0807723814102648, 0.0], "lights": [[0.7, 0.0, 0.0], [0.3, 0.0, 0.0], [0.0, 0.0, 0.0]]}, {"times": {"old_time": 85, "new_time": 86}, "rewards": [2.2734710544859427], "actions": [0], "densities": [6.798594889636766, 2.056540666987185, 0.0], "lights": [[0.7, 0.0, 0.0], [0.3, 0.0, 0.0], [0.0, 0.0, 0.0]]}, {"times": {"old_time": 86, "new_time": 87}, "rewards": [4.464900792626102], "actions": [1], "densities": [6.759016422745735, 2.0395784668910295, 0.0], "lights": [[1.0, 0.0, 0.0], [0.0, 0.0, 0.0], [0.0, 0.0, 0.0]]}, {"times": {"old_time": 87, "new_time": 88}, "rewards": [4.464900792626102], "actions": ["orange"], "densities": [8.759016422745734, 0.0, 0.0], "lights": [[1.0, 0.0, 0.0], [0.0, 0.0, 0.0], [0.0, 0.0, 0.0]]}, {"times": {"old_time": 88, "new_time": 89}, "rewards": [2.1914297381401595], "actions": ["orange"], "densities": [10.759016422745734, 0.0, 0.0], "lights": [[0.30000000000000004, 0.0, 0.0], [0.0, 0.0, 0.0], [0.7, 0.0, 0.0]]}, {"times": {"old_time": 89, "new_time": 90}, "rewards": [1.4], "actions": [0], "densities": [5.227704926823721, 0.0, 7.531311495922013], "lights": [[1.0, 0.0, 0.0], [0.0, 0.0, 0.0], [0.0, 0.0, 0.0]]}, {"times": {"old_time": 89, "new_time": 90}, "rewards": [0], "actions": [0], "densities": [5.227704926823721, 0.0, 7.531311495922013], "lights": [[1.0, 0.0, 0.0], [0.0, 0.0, 0.0], [0.0, 0.0, 0.0]]}], "netName": "net5", "densityName": "random_195"}