{".class": "MypyFile", "_fullname": "z", "is_partial_stub_package": false, "is_stub": false, "names": {".class": "SymbolTable", "Klass": {".class": "SymbolTableNode", "kind": "Gdef", "node": {".class": "TypeInfo", "_promote": null, "abstract_attributes": [], "bases": ["builtins.object"], "declared_metaclass": null, "defn": {".class": "ClassDef", "fullname": "z.Klass", "name": "Klass", "type_vars": []}, "flags": [], "fullname": "z.Klass", "metaclass_type": null, "metadata": {}, "module_name": "z", "mro": ["z.Klass", "builtins.object"], "names": {".class": "SymbolTable"}, "tuple_type": null, "type_vars": [], "typeddict_type": null}}, "__doc__": {".class": "SymbolTableNode", "kind": "Gdef", "node": {".class": "Var", "flags": [], "fullname": "z.__doc__", "name": "__doc__", "type": "builtins.str"}}, "__file__": {".class": "SymbolTableNode", "kind": "Gdef", "node": {".class": "Var", "flags": [], "fullname": "z.__file__", "name": "__file__", "type": "builtins.str"}}, "__hash__": {".class": "SymbolTableNode", "kind": "Gdef", "node": {".class": "FuncDef", "arg_kinds": [0], "arg_names": ["self"], "flags": [], "fullname": "z.__hash__", "name": "__hash__", "type": null}}, "__name__": {".class": "SymbolTableNode", "kind": "Gdef", "node": {".class": "Var", "flags": [], "fullname": "z.__name__", "name": "__name__", "type": "builtins.str"}}, "__package__": {".class": "SymbolTableNode", "kind": "Gdef", "node": {".class": "Var", "flags": [], "fullname": "z.__package__", "name": "__package__", "type": "builtins.str"}}, "functionAssigner": {".class": "SymbolTableNode", "kind": "Gdef", "node": {".class": "FuncDef", "arg_kinds": [], "arg_names": [], "flags": [], "fullname": "z.functionAssigner", "name": "functionAssigner", "type": null}}, "k": {".class": "SymbolTableNode", "kind": "Gdef", "node": {".class": "Var", "flags": [], "fullname": "z.k", "name": "k", "type": "z.Klass"}}}, "path": "C:\\magisterka\\traffic fluid simulator\\backend\\env_4\\z.py"}