{".class": "MypyFile", "_fullname": "model.SaveData", "is_partial_stub_package": false, "is_stub": false, "names": {".class": "SymbolTable", "SaveData": {".class": "SymbolTableNode", "kind": "Gdef", "node": {".class": "TypeInfo", "_promote": null, "abstract_attributes": [], "bases": ["builtins.object"], "declared_metaclass": null, "defn": {".class": "ClassDef", "fullname": "model.SaveData.SaveData", "name": "SaveData", "type_vars": []}, "flags": [], "fullname": "model.SaveData.SaveData", "metaclass_type": null, "metadata": {}, "module_name": "model.SaveData", "mro": ["model.SaveData.SaveData", "builtins.object"], "names": {".class": "SymbolTable", "__init__": {".class": "SymbolTableNode", "kind": "Mdef", "node": {".class": "FuncDef", "arg_kinds": [0, 0, 0], "arg_names": ["self", "learningEpochs", "learningMethod"], "flags": [], "fullname": "model.SaveData.SaveData.__init__", "name": "__init__", "type": null}}, "add_net": {".class": "SymbolTableNode", "kind": "Mdef", "node": {".class": "FuncDef", "arg_kinds": [0, 0], "arg_names": ["self", "globalState"], "flags": [], "fullname": "model.SaveData.SaveData.add_net", "name": "add_net", "type": null}}, "attach_lights": {".class": "SymbolTableNode", "kind": "Mdef", "node": {".class": "FuncDef", "arg_kinds": [0, 0], "arg_names": ["self", "lights"], "flags": [], "fullname": "model.SaveData.SaveData.attach_lights", "name": "attach_lights", "type": null}}, "learningEpochs": {".class": "SymbolTableNode", "implicit": true, "kind": "Mdef", "node": {".class": "Var", "flags": [], "fullname": "model.SaveData.SaveData.learningEpochs", "name": "learningEpochs", "type": {".class": "AnyType", "missing_import_name": null, "source_any": null, "type_of_any": 1}}}, "learningMethod": {".class": "SymbolTableNode", "implicit": true, "kind": "Mdef", "node": {".class": "Var", "flags": [], "fullname": "model.SaveData.SaveData.learningMethod", "name": "learningMethod", "type": {".class": "AnyType", "missing_import_name": null, "source_any": null, "type_of_any": 1}}}, "nets": {".class": "SymbolTableNode", "implicit": true, "kind": "Mdef", "node": {".class": "Var", "flags": [], "fullname": "model.SaveData.SaveData.nets", "name": "nets", "type": {".class": "AnyType", "missing_import_name": null, "source_any": null, "type_of_any": 1}}}}, "tuple_type": null, "type_vars": [], "typeddict_type": null}}, "__doc__": {".class": "SymbolTableNode", "kind": "Gdef", "node": {".class": "Var", "flags": [], "fullname": "model.SaveData.__doc__", "name": "__doc__", "type": "builtins.str"}}, "__file__": {".class": "SymbolTableNode", "kind": "Gdef", "node": {".class": "Var", "flags": [], "fullname": "model.SaveData.__file__", "name": "__file__", "type": "builtins.str"}}, "__name__": {".class": "SymbolTableNode", "kind": "Gdef", "node": {".class": "Var", "flags": [], "fullname": "model.SaveData.__name__", "name": "__name__", "type": "builtins.str"}}, "__package__": {".class": "SymbolTableNode", "kind": "Gdef", "node": {".class": "Var", "flags": [], "fullname": "model.SaveData.__package__", "name": "__package__", "type": "builtins.str"}}, "hash_": {".class": "SymbolTableNode", "kind": "Gdef", "node": {".class": "FuncDef", "arg_kinds": [0], "arg_names": ["action"], "flags": [], "fullname": "model.SaveData.hash_", "name": "hash_", "type": null}}}, "path": "C:\\magisterka\\traffic fluid simulator\\backend\\env_4 \u2014 kopia\\model\\SaveData.py"}